simplepasdassad
