Metadata-Version: 2.1
Name: simplepasdassad
Version: 1.2.1
Summary: parallel, efficient and ensemble analysis of Rao's Q spectral diversity using remote sensing datasets.
Home-page: https://github.com/mmadrz/PaRaVis
Author: Mohammad Reza Fathi
Author-email: mmadrzfathi@gmail.com
License: MIT
